pygubu/__init__.py
pygubu/builder.py
pygubu/i18n.py
pygubu/__pyinstaller/__init__.py
pygubu/__pyinstaller/hook-pygubu.py
pygubu/api/__init__.py
pygubu/api/v1/__init__.py
pygubu/api/v1/_private.py
pygubu/binding/__init__.py
pygubu/binding/base.py
pygubu/binding/bindmanager.py
pygubu/component/__init__.py
pygubu/component/builderobject.py
pygubu/component/plugin_engine.py
pygubu/component/plugin_manager.py
pygubu/component/property_registry.py
pygubu/component/resource.py
pygubu/component/style_manager.py
pygubu/component/uidefinition.py
pygubu/component/widgetmeta.py
pygubu/forms/__init__.py
pygubu/forms/builder.py
pygubu/forms/config.py
pygubu/forms/form.py
pygubu/forms/nouiforms.py
pygubu/forms/pygubuwidget.py
pygubu/forms/tkwidget.py
pygubu/forms/ttkwidget.py
pygubu/forms/widget.py
pygubu/forms/transformer/__init__.py
pygubu/forms/transformer/tkboolean.py
pygubu/forms/validation/__init__.py
pygubu/forms/validation/base.py
pygubu/forms/validation/constraint/__init__.py
pygubu/forms/validation/constraint/form.py
pygubu/forms/validation/constraint/istrue.py
pygubu/forms/validation/constraint/notblank.py
pygubu/plugins/__init__.py
pygubu/plugins/awesometkinter/__init__.py
pygubu/plugins/awesometkinter/button.py
pygubu/plugins/awesometkinter/frame.py
pygubu/plugins/awesometkinter/label.py
pygubu/plugins/awesometkinter/progressbar.py
pygubu/plugins/awesometkinter/scrollbar.py
pygubu/plugins/awesometkinter/text.py
pygubu/plugins/awesometkinter/designer/__init__.py
pygubu/plugins/awesometkinter/designer/designerplugin.py
pygubu/plugins/awesometkinter/designer/properties.py
pygubu/plugins/customtkinter/__init__.py
pygubu/plugins/customtkinter/ctkbase.py
pygubu/plugins/customtkinter/scrollableframe.py
pygubu/plugins/customtkinter/tabview.py
pygubu/plugins/customtkinter/widgets.py
pygubu/plugins/customtkinter/windows.py
pygubu/plugins/customtkinter/designer/__init__.py
pygubu/plugins/customtkinter/designer/designerplugin.py
pygubu/plugins/customtkinter/designer/preview.py
pygubu-0.40.dist-info/licenses/AUTHORS
pygubu-0.40.dist-info/licenses/LICENSE
pygubu-0.40.dist-info/METADATA
pygubu-0.40.dist-info/WHEEL
pygubu-0.40.dist-info/entry_points.txt
pygubu-0.40.dist-info/top_level.txt
pygubu-0.40.dist-info/RECORD
