Metadata-Version: 2.4
Name: pygubu
Version: 0.40
Summary: A simple GUI builder for the python tkinter module
Author-email: Alejandro Autalan <alejandroautalan@gmail.com>
License-Expression: MIT
Project-URL: Documentation, https://github.com/alejandroautalan/pygubu#readme
Project-URL: Issues, https://github.com/alejandroautalan/pygubu/issues
Project-URL: Source, https://github.com/alejandroautalan/pygubu
Keywords: gui,tkinter,designer
Classifier: Development Status :: 4 - Beta
Classifier: Programming Language :: Python
Classifier: Programming Language :: Python :: 3.9
Classifier: Programming Language :: Python :: 3.10
Classifier: Programming Language :: Python :: 3.11
Classifier: Programming Language :: Python :: 3.12
Classifier: Programming Language :: Python :: 3.13
Classifier: Programming Language :: Python :: 3.14
Classifier: Operating System :: OS Independent
Classifier: Intended Audience :: Developers
Classifier: Topic :: Software Development :: Libraries :: Python Modules
Classifier: Topic :: Utilities
Classifier: Topic :: Software Development :: User Interfaces
Requires-Python: >=3.9
License-File: LICENSE
License-File: AUTHORS
Requires-Dist: importlib_metadata>=3.6; python_version < "3.10"
Provides-Extra: ttkwidgets
Requires-Dist: ttkwidgets; extra == "ttkwidgets"
Provides-Extra: tksheet
Requires-Dist: tksheet; extra == "tksheet"
Provides-Extra: tkinterweb
Requires-Dist: tkinterweb; extra == "tkinterweb"
Provides-Extra: tkintertable
Requires-Dist: tkintertable; extra == "tkintertable"
Provides-Extra: tkcalendar
Requires-Dist: tkcalendar; extra == "tkcalendar"
Provides-Extra: awesometkinter
Requires-Dist: AwesomeTkinter; extra == "awesometkinter"
Provides-Extra: customtkinter
Requires-Dist: customtkinter>=5.2.2; extra == "customtkinter"
Requires-Dist: packaging; extra == "customtkinter"
Requires-Dist: pillow; extra == "customtkinter"
Provides-Extra: tkintermapview
Requires-Dist: tkintermapview; extra == "tkintermapview"
Provides-Extra: all
Requires-Dist: AwesomeTkinter; extra == "all"
Requires-Dist: tkintertable; extra == "all"
Requires-Dist: tksheet; extra == "all"
Requires-Dist: ttkwidgets; extra == "all"
Requires-Dist: tkinterweb; extra == "all"
Requires-Dist: tkcalendar; extra == "all"
Requires-Dist: customtkinter>=5.2.2; extra == "all"
Requires-Dist: packaging; extra == "all"
Requires-Dist: pillow; extra == "all"
Requires-Dist: tkintermapview; extra == "all"
Dynamic: license-file
